halonex/__init__.py
halonex/exceptions.py
halonex/db/__init__.py
halonex/db/config.py
halonex/db/firebase_log.py
halonex/db/json_safe.py
halonex/db/postgres.py
halonex/tools/endpoint_parser.py
halonex/vanta/__init__.py
halonex/vanta/validator.py
halonex-0.1.9.dist-info/METADATA
halonex-0.1.9.dist-info/WHEEL
halonex-0.1.9.dist-info/top_level.txt
halonex-0.1.9.dist-info/RECORD
